{
  "required": true,
  "package": "chronosacaria.mcdw.mixin",
  "compatibilityLevel": "JAVA_8",
  "mixins": [
    "AccessorItemTags",
    "MixinEntity",
    "enchantments.AnimaConduitEnchantmentMixin",
    "enchantments.BonusShotEnchantmentMixin",
    "enchantments.BusyBeeEnchantmentMixin",
    "enchantments.ChainReactionEnchantmentMixin",
    "enchantments.ChainsEnchantmentMixin",
    "enchantments.ChargeEnchantmentMixin",
    "enchantments.CommittedEnchantmentsMixin",
    "enchantments.CriticalHitEnchantmentMixin",
    "enchantments.EchoEnchantmentMixin",
    "enchantments.ExplodingEnchantmentMixin",
    "enchantments.FreezingEnchantmentMixin",
    "enchantments.FuseShotEnchantmentMixin",
    "enchantments.GravityEnchantmentMixin",
    "enchantments.GrowingEnchantmentMixin",
    "enchantments.JunglesPoisonEnchantmentMixin",
    "enchantments.LeechingEnchantmentMixin",
    "enchantments.PoisonCloudEnchantmentMixin",
    "enchantments.ProspectorEnchantmentMixin",
    "enchantments.RadianceEnchantmentMixin",
    "enchantments.RadianceShotEnchantmentMixin",
    "enchantments.RampagingEnchantmentMixin",
    "enchantments.ReplenishEnchantmentMixin",
    "enchantments.RicochetEnchantmentMixin",
    "enchantments.ShockwaveEnchantmentMixin",
    "enchantments.SmitingEnchantmentMixin",
    "enchantments.SoulSiphonEnchantmentMixin",
    "enchantments.StunningEnchantmentMixin",
    "enchantments.SwirlingEnchantmentMixin",
    "enchantments.TempoTheftEnchantmentMixin",
    "enchantments.ThunderingEnchantmentMixin",
    "enchantments.WeakeningEnchantmentMixin",
    "LivingEntityMixin"
  ],
  "client": [
  ],
  "injectors": {
    "defaultRequire": 1
  }
}